README.txt
TODO
setup.cfg
setup.py
svnignore.sh
docs/HISTORY.txt
docs/INSTALL.txt
docs/LICENSE.GPL
docs/LICENSE.txt
src/collective/__init__.py
src/collective.z3cform.grok.egg-info/PKG-INFO
src/collective.z3cform.grok.egg-info/SOURCES.txt
src/collective.z3cform.grok.egg-info/dependency_links.txt
src/collective.z3cform.grok.egg-info/namespace_packages.txt
src/collective.z3cform.grok.egg-info/requires.txt
src/collective.z3cform.grok.egg-info/top_level.txt
src/collective/z3cform/__init__.py
src/collective/z3cform/grok/__init__.py
src/collective/z3cform/grok/configure.zcml
src/collective/z3cform/grok/grok.py
src/collective/z3cform/grok/tests/__init__.py
src/collective/z3cform/grok/tests/base.py
src/collective/z3cform/grok/tests/form.txt
src/collective/z3cform/grok/tests/globals.py
src/collective/z3cform/grok/tests/test_doctests.py
src/collective/z3cform/grok/tests/user_testcase.py
src/collective/z3cform/grok/tests/utils.py
src/collective/z3cform/grok/tests/form_templates/myview.pt