Metadata-Version: 1.0
Name: collective.z3cform.grok
Version: 1.15
Summary: A small integration of z3cform using grok magic on plone by Makina Corpus.
Home-page: http://svn.plone.org/svn/collective/collective.z3cform.grok
Author: Mathieu Pasquet
Author-email: kiorky@cryptelium.net
License: GPL
Platform: UNKNOWN
Classifier: Programming Language :: Python
Classifier: Topic :: Software Development
Classifier: Framework :: Plone
Classifier: Programming Language :: Zope
Classifier: Framework :: Zope2
Classifier: Framework :: Zope3
Classifier: Topic :: Software Development :: Libraries :: Python Modules
